setup.py
mlaricobar_probability/Binomialdistribution.py
mlaricobar_probability/Gaussiandistribution.py
mlaricobar_probability/Generaldistribution.py
mlaricobar_probability/__init__.py
mlaricobar_probability.egg-info/PKG-INFO
mlaricobar_probability.egg-info/SOURCES.txt
mlaricobar_probability.egg-info/dependency_links.txt
mlaricobar_probability.egg-info/not-zip-safe
mlaricobar_probability.egg-info/top_level.txt