Metadata-Version: 1.0
Name: mlaricobar-probability
Version: 0.1
Summary: Gaussian and binomial distribution
Home-page: UNKNOWN
Author: Michael Larico Barzola
Author-email: mlaricobar@gmail.com
License: UNKNOWN
Platform: UNKNOWN
